omniadapters/__init__.py
omniadapters/py.typed
omniadapters/.tiktoken_cache/9b5ad71b2ce5302211f9c61530b329a4922fc6a4
omniadapters/.tiktoken_cache/fb374d419588a4632f3f557e76b4b70aebbca790
omniadapters/completion/__init__.py
omniadapters/completion/factory.py
omniadapters/completion/adapters/__init__.py
omniadapters/completion/adapters/anthropic.py
omniadapters/completion/adapters/azure_openai.py
omniadapters/completion/adapters/base.py
omniadapters/completion/adapters/gemini.py
omniadapters/completion/adapters/openai.py
omniadapters/core/__init__.py
omniadapters/core/constants.py
omniadapters/core/enums.py
omniadapters/core/models.py
omniadapters/core/protocols.py
omniadapters/core/tokens.py
omniadapters/core/types.py
omniadapters/core/usage.py
omniadapters/core/usage_converter.py
omniadapters/pydantic_ai/__init__.py
omniadapters/pydantic_ai/adapter.py
omniadapters/pydantic_ai/factory.py
omniadapters/structify/__init__.py
omniadapters/structify/factory.py
omniadapters/structify/hooks.py
omniadapters/structify/models.py
omniadapters/structify/adapters/__init__.py
omniadapters/structify/adapters/anthropic.py
omniadapters/structify/adapters/azure_openai.py
omniadapters/structify/adapters/base.py
omniadapters/structify/adapters/gemini.py
omniadapters/structify/adapters/openai.py
omniadapters-26.0.0.dist-info/METADATA
omniadapters-26.0.0.dist-info/WHEEL
omniadapters-26.0.0.dist-info/RECORD
