Metadata-Version: 2.4
Name: omniadapters
Version: 26.0.0
Summary: A collection of code for omniadapters - unified interfaces for LLM providers.
Project-URL: Homepage, https://github.com/gao-hongnan/omniadapters
Project-URL: Documentation, https://github.com/gao-hongnan/omniadapters/tree/main/playbook
Project-URL: Repository, https://github.com/gao-hongnan/omniadapters
Project-URL: Issues, https://github.com/gao-hongnan/omniadapters/issues
Project-URL: Changelog, https://github.com/gao-hongnan/omniadapters/releases
Author-email: GAO Hongnan <hongnangao@gmail.com>
Maintainer-email: GAO Hongnan <hongnangao@gmail.com>
License: Apache-2.0
Keywords: adapters,ai,anthropic,gemini,google,instructor,llm,openai,pydantic,structured-output
Classifier: Development Status :: 4 - Beta
Classifier: Intended Audience :: Developers
Classifier: License :: OSI Approved :: Apache Software License
Classifier: Operating System :: OS Independent
Classifier: Programming Language :: Python :: 3
Classifier: Programming Language :: Python :: 3.12
Classifier: Programming Language :: Python :: 3.13
Classifier: Topic :: Scientific/Engineering :: Artificial Intelligence
Classifier: Topic :: Software Development :: Libraries :: Python Modules
Classifier: Typing :: Typed
Requires-Python: >=3.12
Requires-Dist: instructor>=1.13.0
Requires-Dist: jsonref<2.0.0,>=1.1.0
Requires-Dist: pydantic-settings<2.12.0,>=2.11.0
Requires-Dist: pydantic<2.13.0,>=2.12.0
Provides-Extra: all
Requires-Dist: anthropic<1.0.0,>=0.72.0; extra == 'all'
Requires-Dist: google-genai==1.50.1; extra == 'all'
Requires-Dist: openai<3.0.0,>=2.8.0; extra == 'all'
Requires-Dist: pydantic-ai>=0.2.0; extra == 'all'
Requires-Dist: tiktoken>=0.12.0; extra == 'all'
Provides-Extra: anthropic
Requires-Dist: anthropic<1.0.0,>=0.72.0; extra == 'anthropic'
Provides-Extra: gemini
Requires-Dist: google-genai==1.50.1; extra == 'gemini'
Provides-Extra: openai
Requires-Dist: openai<3.0.0,>=2.8.0; extra == 'openai'
Provides-Extra: playground
Requires-Dist: pydanticonf>=1.0.0; extra == 'playground'
Provides-Extra: pydantic-ai
Requires-Dist: pydantic-ai>=0.2.0; extra == 'pydantic-ai'
Provides-Extra: token
Requires-Dist: tiktoken>=0.12.0; extra == 'token'
